bespoken/__init__.py
bespoken/__main__.py
bespoken/config.py
bespoken/file_completer.py
bespoken/not_installed.py
bespoken/ui.py
bespoken/prompts/__init__.py
bespoken/prompts/_marimo.py
bespoken/tools/__init__.py
bespoken/tools/command.py
bespoken/tools/filesystem.py
bespoken/tools/playwright_browser.py
bespoken/tools/todo.py
bespoken/tools/webfetch.py
bespoken-0.2.2.dist-info/licenses/LICENSE
bespoken-0.2.2.dist-info/METADATA
bespoken-0.2.2.dist-info/WHEEL
bespoken-0.2.2.dist-info/entry_points.txt
bespoken-0.2.2.dist-info/top_level.txt
bespoken-0.2.2.dist-info/RECORD
