Metadata-Version: 2.4
Name: bespoken
Version: 0.2.2
Summary: A toolbox to build your own assistant for in the terminal.
Author-email: Your Name <your.email@example.com>
License: MIT
Project-URL: Homepage, https://github.com/yourusername/bespoken
Project-URL: Documentation, https://github.com/yourusername/bespoken#readme
Project-URL: Repository, https://github.com/yourusername/bespoken.git
Project-URL: Issues, https://github.com/yourusername/bespoken/issues
Keywords: ai,assistant,llm,code-editor,marimo
Classifier: Development Status :: 3 - Alpha
Classifier: Intended Audience :: Developers
Classifier: License :: OSI Approved :: MIT License
Classifier: Programming Language :: Python :: 3
Classifier: Programming Language :: Python :: 3.8
Classifier: Programming Language :: Python :: 3.9
Classifier: Programming Language :: Python :: 3.10
Classifier: Programming Language :: Python :: 3.11
Classifier: Programming Language :: Python :: 3.12
Requires-Python: >=3.8
License-File: LICENSE
Requires-Dist: llm>=0.12
Requires-Dist: rich>=13.0.0
Requires-Dist: python-dotenv>=1.0.0
Requires-Dist: typer>=0.9.0
Requires-Dist: requests>=2.31.0
Requires-Dist: beautifulsoup4>=4.12.0
Requires-Dist: markdownify>=0.11.0
Requires-Dist: prompt_toolkit>=3.0.0
Requires-Dist: questionary>=1.10.0
Provides-Extra: dev
Requires-Dist: pytest>=7.0; extra == "dev"
Requires-Dist: pytest-cov>=4.0; extra == "dev"
Requires-Dist: black>=23.0; extra == "dev"
Requires-Dist: ruff>=0.1.0; extra == "dev"
Requires-Dist: mypy>=1.0; extra == "dev"
Provides-Extra: browser
Requires-Dist: playwright>=1.40.0; extra == "browser"
Dynamic: license-file
